TestLibrary/__init__.py
TestLibrary/hello.py
HelloPyPI_Project-0.0.1.dist-info/METADATA
HelloPyPI_Project-0.0.1.dist-info/WHEEL
HelloPyPI_Project-0.0.1.dist-info/top_level.txt
HelloPyPI_Project-0.0.1.dist-info/RECORD
