Metadata-Version: 2.1
Name: HelloPyPI_Project
Version: 0.0.1
Summary: First Python Package in PyPI
Author: Baburam Chaudhary
Author-email: <baburam.ch208@gmail.com>
Keywords: python,python package
Classifier: Development Status :: 1 - Planning
Classifier: Intended Audience :: Developers
Classifier: Programming Language :: Python :: 3
Classifier: Operating System :: Unix
Classifier: Operating System :: MacOS :: MacOS X
Classifier: Operating System :: Microsoft :: Windows
Requires-Dist: setuptools
